{
  "navigation": {
    "home": "HOME",
    "notice": "公示",
    "sailingInstructions": "帆走指示書",
    "participants": "参加艇",
    "pastEvents": "過去大会の様子",
    "contact": "お問い合わせ"
  },
  "header": {
    "menuTitle": "メニュー",
    "languageSwitch": "言語切替",
    "entryOpen": "エントリー受付中"
  },
  "footer": {
    "links": "リンク",
    "contactUs": "お問い合わせ",
    "contactText": "大会に関するお問い合わせは、お問い合わせフォームよりお願いいたします。",
    "copyright": "Copyright © 2025 Taiwan Ryukyu Regatta. All Rights Reserved."
  },
  "home": {
    "mainTitle": "第21回台琉友好親善国際ヨットレース",
    "subtitle": "（基隆市・宮古島市 国際交流事業）",
    "slogan": "沖縄の宮古島から、世界の宮古島へ！！",
    "eventDate": "2025年6月7日〜12日 台湾基隆市・宮古島市にて開催",
    "applyButton": "参加申込はこちら",
    "detailsButton": "大会詳細を見る",
    "latestNews": "最新情報",
    "newsCategory": {
      "announcement": "お知らせ",
      "event": "イベント"
    },
    "overview": "開催概要",
    "schedule": "開催日程",
    "venue": "開催地",
    "contact": "お問い合わせ"
  },
  "notice": {
    "title": "公示",
    "downloadButton": "公示PDFをダウンロード"
  },
  "sailingInstructions": {
    "title": "帆走指示書",
    "fullText": "2025帆走指示書",
    "fullTextDesc": "帆走指示書の全文PDFです。",
    "selfDeclaration": "Self Declaration Form",
    "selfDeclarationDesc": "自我申告書のPDFフォームです。",
    "download": "ダウンロード",
    "contactText": "帆走指示書に関するご質問は、大会事務局までお問い合わせください。",
    "contactLink": "お問い合わせはこちら"
  },
  "participants": {
    "title": "参加艇",
    "japanese": "日本参加艇",
    "international": "海外参加艇",
    "preparingInfo": "参加艇の情報は準備中です",
    "noticeTitle": "参加艇の皆様へ"
  },
  "pastEvents": {
    "title": "過去大会の様子",
    "videoTitle": "2023年大会動画",
    "videoDesc": "2023年台湾琉球国際ヨットレースのハイライト映像",
    "browserNotSupported": "お使いのブラウザは動画の再生に対応していません。"
  },
  "contact": {
    "title": "お問い合わせ",
    "loading": "読み込んでいます…"
  },
  "common": {
    "breadcrumbHome": "HOME"
  }
}

